<?xml version="1.0" encoding="utf-8"?>
<ArrayOfDependence>
  <Dependence>
    <Id>1</Id>
    <DependentOnTask>1</DependentOnTask>
    <DependentTask>2</DependentTask>
  </Dependence>
  <Dependence>
    <Id>2</Id>
    <DependentOnTask>2</DependentOnTask>
    <DependentTask>3</DependentTask>
  </Dependence>
  <Dependence>
    <Id>3</Id>
    <DependentOnTask>3</DependentOnTask>
    <DependentTask>4</DependentTask>
  </Dependence>
  <Dependence>
    <Id>4</Id>
    <DependentOnTask>4</DependentOnTask>
    <DependentTask>5</DependentTask>
  </Dependence>
  <Dependence>
    <Id>5</Id>
    <DependentOnTask>6</DependentOnTask>
    <DependentTask>2</DependentTask>
  </Dependence>
  <Dependence>
    <Id>6</Id>
    <DependentOnTask>5</DependentOnTask>
    <DependentTask>9</DependentTask>
  </Dependence>
  <Dependence>
    <Id>7</Id>
    <DependentOnTask>5</DependentOnTask>
    <DependentTask>2</DependentTask>
  </Dependence>
  <Dependence>
    <Id>8</Id>
    <DependentOnTask>7</DependentOnTask>
    <DependentTask>2</DependentTask>
  </Dependence>
  <Dependence>
    <Id>9</Id>
    <DependentOnTask>4</DependentOnTask>
    <DependentTask>7</DependentTask>
  </Dependence>
</ArrayOfDependence>