<?xml version="1.0" encoding="utf-8"?>
<ArrayOfEngineer>
	<Engineer>
		<Id>329736466</Id>
		<Name>Racheli toledano</Name>
		<Email>rt@gmail.com</Email>
		<Level> Beginner</Level>
		<Cost>200.00</Cost>
		<Active> true </Active>
	</Engineer>

	<Engineer>
		<Id>325531671</Id>
		<Name>Sara Blass</Name>
		<Email>saraBlass@gmail.com</Email>
		<Level> AdvancedBeginner</Level>
		<Cost>400.00</Cost>
		<Active> true </Active>
	</Engineer>

	<Engineer>
		<Id>214490195</Id>
		<Name>Brachi Kim</Name>
		<Email>Brachikim@gmail.com</Email>
		<Level> Competent</Level>
		<Active> false </Active>
	</Engineer>

	<Engineer>
		<Id>322311317</Id>
		<Name>Ruti Leybuvi</Name>
		<Email>ruti@gmail.com</Email>
		<Level>Proficient</Level>
		<Cost>1000.00</Cost>
		<Active> true </Active>
	</Engineer>

	<Engineer>
		<Id>326202454</Id>
		<Name>Osnat Shachor</Name>
		<Email>osnat@gmail.com</Email>
		<Level>Expert</Level>
		<Cost>1200.00</Cost>
		<Active> true </Active>
	</Engineer>

	<Engineer>
		<Id>324567866</Id>
		<Name>Avigail Ginzburg</Name>
		<Email>Avigail@gmail.com</Email>
		<Level>Beginner</Level>
		<Cost>200.00</Cost>
		<Active>true</Active>
	</Engineer>

	<Engineer>
		<Id>231562896</Id>
		<Name>Cani Levi</Name>
		<Email>Cani@gmail.com</Email>
		<Level>AdvancedBeginner</Level>
		<Cost>400.00</Cost>
		<Active>true</Active>
	</Engineer>

	<Engineer>
		<Id>234769342</Id>
		<Name>Tamar Mitelman</Name>
		<Email>TamarM910@gmail.com</Email>
		<Level>Competent</Level>
		<Active>false </Active>
	</Engineer>

	<Engineer>
		<Id>324567876</Id>
		<Name>Yosef Berko</Name>
		<Email>yosBerko@gmail.com</Email>
		<Level>Proficient</Level>
		<Cost>1000.00</Cost>
		<Active> true </Active>
	</Engineer>

	<Engineer>
		<Id>231287455</Id>
		<Name>Motti Golo</Name>
		<Email>mottigolo2365@gmail.com</Email>
		<Level>Expert</Level>
		<Active>false</Active>
	</Engineer>

</ArrayOfEngineer>
